{
  "packageId": "app.okauto.twa",
  "host": "okauto.app",
  "name": "OK AUTO: Redefining Rental Convenience",
  "launcherName": "OK AUTO",
  "display": "fullscreen",
  "themeColor": "#489EFD",
  "themeColorDark": "#000000",
  "navigationColor": "#000000",
  "navigationColorDark": "#000000",
  "navigationDividerColor": "#000000",
  "navigationDividerColorDark": "#000000",
  "backgroundColor": "#FFFFFF",
  "enableNotifications": true,
  "startUrl": "/",
  "iconUrl": "https://okauto.app/assets/images/logo_icon/Screenshot_2025-04-06_152847-removebg-preview%20(2).png",
  "maskableIconUrl": "https://okauto.app/assets/images/logo_icon/Screenshot_2025-04-06_152847-removebg-preview%20(2).png",
  "splashScreenFadeOutDuration": 300,
  "signingKey": {
    "path": "/var/www/html/okauto.app/android.keystore",
    "alias": "android"
  },
  "appVersionName": "1",
  "appVersionCode": 1,
  "shortcuts": [],
  "generatorApp": "bubblewrap-cli",
  "webManifestUrl": "https://okauto.app/manifest-en.json",
  "fallbackType": "customtabs",
  "features": {},
  "alphaDependencies": {
    "enabled": false
  },
  "enableSiteSettingsShortcut": true,
  "isChromeOSOnly": false,
  "isMetaQuest": false,
  "fullScopeUrl": "https://okauto.app/",
  "minSdkVersion": 21,
  "orientation": "portrait",
  "fingerprints": [],
  "additionalTrustedOrigins": [],
  "retainedBundles": [],
  "protocolHandlers": [],
  "appVersion": "1"
}